{
  "appid": "wx4cb8a7c3b93d9a52",
  "compileType": "miniprogram",
  "libVersion": "3.6.0",
  "packOptions": {
    "ignore": [
      {
        "value": "/minitest",
        "type": "folder"
      }
    ],
    "include": []
  },
  "setting": {
    "coverView": true,
    "es6": true,
    "postcss": true,
    "minified": true,
    "enhance": true,
    "showShadowRootInWxmlPanel": true,
    "packNpmRelationList": [],
    "babelSetting": {
      "ignore": [],
      "disablePlugins": [],
      "outputPath": ""
    }
  },
  "condition": {},
  "editorSetting": {
    "tabIndent": "insertSpaces",
    "tabSize": 2
  },
  "testRoot": "minitest/"
}